{
  "users": [
    {
      "id": 1,
      "email": "mer.marcosr@gmail.com",
      "password": "test",
      "userType": "student",
      "firstName": "Marcos Ezequiel",
      "lastName": "Rodriguez",
      "primary": "complete",
      "secundary": "complete",
      "universitary": "ongoing",
      "terciary": "complete",
      "birthDate": "1994-02-22",
      "telNumber": "11223344"
    },
    {
      "id": 2,
      "email": "levignafranco@gmail.com",
      "password": "123",
      "userType": "professor",
      "firstName": "Franco",
      "lastName": "Levigna",
      "degree": "Licenciado en Sistemas",
      "experience": "Microservicios con python, diversas bases de datos tanto NoSQL como SQL, docker, Cloud (Principalmente AWS) "
    },
    {
      "id": 3,
      "email": "jackwhite@email.com",
      "password": "test",
      "telNumber": "12345678",
      "userType": "professor",
      "firstName": "Jack",
      "lastName": "White"
    }
  ],
  "classes": [
    {
      "id": 1,
      "professor": {
        "id": 1,
        "name": "Lion Jouhandeau",
        "experience": "Profesional del area con mas de 10 años de trayectoria."
      },
      "status": "published",
      "comments": [
        {
          "message": "Me hubiera gustado que profundice más en algunos temas, pero la clase es de calidad",
          "date": "9/25/2021",
          "user": {
            "id": 9,
            "name": "Otto Ottis",
            "rating": 3
          }
        },
        {
          "message": "La mejor clase",
          "date": "12/1/2021",
          "user": {
            "id": 10,
            "name": "Ruby Rubin",
            "rating": 3
          }
        },
        {
          "message": "Muy buena clase, aprendi muchisimo",
          "date": "2/3/2022",
          "user": {
            "id": 11,
            "name": "Kit Kat",
            "rating": 3
          }
        }
      ],
      "name": "Literatura",
      "cost": "$76.93",
      "frequency": "weekly",
      "duration": 1,
      "rating": 3.6,
      "type": "individual",
      "description": "El teatro es literatura destinada a la representación. Casi todos los dramas tomaron forma de verso hasta hace relativamente poco tiempo."
    },
    {
      "id": 2,
      "professor": {
        "id": 2,
        "name": "Andi Burk",
        "experience": "Profesional del area con mas de 10 años de trayectoria."
      },
      "status": "published",
      "comments": [
        {
          "message": "Me hubiera gustado que profundice más en algunos temas, pero la clase es de calidad",
          "date": "9/25/2021",
          "user": {
            "id": 9,
            "name": "Otto Ottis",
            "rating": 3
          }
        },
        {
          "message": "La mejor clase",
          "date": "12/1/2021",
          "user": {
            "id": 10,
            "name": "Ruby Rubin",
            "rating": 3
          }
        },
        {
          "message": "Muy buena clase, aprendi muchisimo",
          "date": "2/3/2022",
          "user": {
            "id": 11,
            "name": "Kit Kat",
            "rating": 3
          }
        }
      ],
      "name": "Química",
      "cost": "$29.88",
      "frequency": "monthly",
      "duration": 2,
      "rating": 2.7,
      "type": "individual",
      "description": "La definición de química ha cambiado con el tiempo, a medida que nuevos descubrimientos y teorías se suman a la funcionalidad de la ciencia."
    },
    {
      "id": 3,
      "professor": {
        "id": 3,
        "name": "Tanney Hinchon",
        "experience": "Profesional del area con mas de 10 años de trayectoria."
      },
      "status": "published",
      "comments": [
        {
          "message": "Me hubiera gustado que profundice más en algunos temas, pero la clase es de calidad",
          "date": "9/25/2021",
          "user": {
            "id": 9,
            "name": "Otto Ottis",
            "rating": 3
          }
        },
        {
          "message": "La mejor clase",
          "date": "12/1/2021",
          "user": {
            "id": 10,
            "name": "Ruby Rubin",
            "rating": 3
          }
        },
        {
          "message": "Muy buena clase, aprendi muchisimo",
          "date": "2/3/2022",
          "user": {
            "id": 11,
            "name": "Kit Kat",
            "rating": 3
          }
        }
      ],
      "name": "Parlando italiano",
      "cost": "$84.91",
      "frequency": "unique",
      "duration": 3,
      "rating": 4.9,
      "type": "groupal",
      "description": "Within the Catholic Church, Italian is known by a large part of the ecclesiastical hierarchy and is used in substitution for Latin in some official documents.",
      "subject": "Italiano"
    },
    {
      "id": 4,
      "professor": {
        "id": 4,
        "name": "Eden Deaconson",
        "experience": "Profesional del area con mas de 10 años de trayectoria."
      },
      "status": "published",
      "comments": [
        {
          "message": "Me hubiera gustado que profundice más en algunos temas, pero la clase es de calidad",
          "date": "9/25/2021",
          "user": {
            "id": 9,
            "name": "Otto Ottis",
            "rating": 3
          }
        },
        {
          "message": "La mejor clase",
          "date": "12/1/2021",
          "user": {
            "id": 10,
            "name": "Ruby Rubin",
            "rating": 3
          }
        },
        {
          "message": "Muy buena clase, aprendi muchisimo",
          "date": "2/3/2022",
          "user": {
            "id": 11,
            "name": "Kit Kat",
            "rating": 3
          }
        }
      ],
      "name": "Ingles",
      "cost": "$8.02",
      "frequency": "monthly",
      "duration": 4,
      "rating": 4,
      "type": "groupal",
      "description": "The phonetics and phonology of the English language differ from one dialect to another, usually without interfering with mutual communication."
    },
    {
      "id": 5,
      "professor": {
        "id": 5,
        "name": "Roña Castro",
        "experience": "Profesional del area con mas de 10 años de trayectoria."
      },
      "status": "published",
      "comments": [
        {
          "message": "Me hubiera gustado que profundice más en algunos temas, pero la clase es de calidad",
          "date": "9/25/2021",
          "user": {
            "id": 9,
            "name": "Otto Ottis",
            "rating": 3
          }
        },
        {
          "message": "La mejor clase",
          "date": "12/1/2021",
          "user": {
            "id": 10,
            "name": "Ruby Rubin",
            "rating": 3
          }
        },
        {
          "message": "Muy buena clase, aprendi muchisimo",
          "date": "2/3/2022",
          "user": {
            "id": 11,
            "name": "Kit Kat",
            "rating": 3
          }
        }
      ],
      "name": "Guitarra",
      "cost": "$29.88",
      "frequency": "monthly",
      "duration": 2,
      "rating": 3,
      "type": "individual",
      "description": "Curso de guitarra por fax del profesor Roña Castro"
    },
    {
      "id": 6,
      "professor": {
        "id": 6,
        "name": "Tanney Hinchon",
        "experience": "Profesional del area con mas de 10 años de trayectoria."
      },
      "status": "published",
      "comments": [
        {
          "message": "Me hubiera gustado que profundice más en algunos temas, pero la clase es de calidad",
          "date": "9/25/2021",
          "user": {
            "id": 9,
            "name": "Otto Ottis",
            "rating": 3
          }
        },
        {
          "message": "La mejor clase",
          "date": "12/1/2021",
          "user": {
            "id": 10,
            "name": "Ruby Rubin",
            "rating": 3
          }
        },
        {
          "message": "Muy buena clase, aprendi muchisimo",
          "date": "2/3/2022",
          "user": {
            "id": 11,
            "name": "Kit Kat",
            "rating": 3
          }
        }
      ],
      "name": "Electricidad Domiciliaria",
      "cost": "$84.91",
      "frequency": "unique",
      "duration": 3,
      "rating": 3,
      "type": "groupal",
      "description": "Para que no te vayas a eloctrocucutar, ni que tu mamá corte toda la luz"
    },
    {
      "id": 7,
      "professor": {
        "id": 7,
        "name": "Reinaldo Merlo",
        "experience": "Profesional del area con mas de 10 años de trayectoria."
      },
      "status": "published",
      "comments": [
        {
          "message": "Me hubiera gustado que profundice más en algunos temas, pero la clase es de calidad",
          "date": "9/25/2021",
          "user": {
            "id": 9,
            "name": "Otto Ottis",
            "rating": 3
          }
        },
        {
          "message": "La mejor clase",
          "date": "12/1/2021",
          "user": {
            "id": 10,
            "name": "Ruby Rubin",
            "rating": 3
          }
        },
        {
          "message": "Muy buena clase, aprendi muchisimo",
          "date": "2/3/2022",
          "user": {
            "id": 11,
            "name": "Kit Kat",
            "rating": 3
          }
        }
      ],
      "name": "Guitarra y canto",
      "cost": "$29.88",
      "frequency": "weekly",
      "duration": 15,
      "rating": 5,
      "type": "individual",
      "description": "A no desanimarse, con el curso de guitarra y canto por fax de Mostaza Merlo sacas Confesiones de Invierno en 15 semanas!"
    },
    {
      "id": 8,
      "professor": {
        "id": 8,
        "name": "Tanney Hinchon",
        "experience": "Profesional del area con mas de 10 años de trayectoria."
      },
      "status": "published",
      "comments": [
        {
          "message": "Me hubiera gustado que profundice más en algunos temas, pero la clase es de calidad",
          "date": "9/25/2021",
          "user": {
            "id": 9,
            "name": "Otto Ottis",
            "rating": 3
          }
        },
        {
          "message": "La mejor clase",
          "date": "12/1/2021",
          "user": {
            "id": 10,
            "name": "Ruby Rubin",
            "rating": 3
          }
        },
        {
          "message": "Muy buena clase, aprendi muchisimo",
          "date": "2/3/2022",
          "user": {
            "id": 11,
            "name": "Kit Kat",
            "rating": 3
          }
        }
      ],
      "name": "Construcción",
      "cost": "$84.91",
      "frequency": "weekly",
      "duration": 3,
      "rating": 3,
      "type": "groupal",
      "description": "Te haces la casa"
    },
    {
      "name": "Python con Fran",
      "subject": "Python",
      "description": "Vamos a aprender con ejemplos de la vida real",
      "duration": "1",
      "frequency": "unique",
      "cost": "100",
      "type": "individual",
      "status": "published",
      "professor": {
        "id": 2,
        "name": "Franco Levigna",
        "experience": "Microservicios con python, diversas bases de datos tanto NoSQL como SQL, docker, Cloud (Principalmente AWS) "
      },
      "id": 9
    },
    {
      "name": "React Native con Fran",
      "subject": "React Native",
      "description": "Vamos a aprender React con ejemplos de la vida real.",
      "duration": "1",
      "frequency": "weekly",
      "cost": "100",
      "type": "individual",
      "status": "published",
      "professor": {
        "id": 2,
        "name": "Franco Levigna",
        "experience": "Microservicios con python, diversas bases de datos tanto NoSQL como SQL, docker, Cloud (Principalmente AWS) "
      },
      "id": 10
    }
  ],
  "classes_students": [
    {
      "email": "mer.marcosr@gmail.com",
      "telNumber": "987654321",
      "contactSchedule": "de 6 a 8pm",
      "message": "Me gusta el arte",
      "userId": 2,
      "classId": 9,
      "studentName": "Marcos Ezequiel Rodriguez",
      "status": "requested",
      "id": 1
    },
    {
      "email": "mer.marcosr@gmail.com",
      "telNumber": "11223344",
      "contactSchedule": "De 6 a 8pm",
      "message": "Quiero aprender con ejemplos de la vida real, como comentas en la descripción de la clase",
      "userId": 2,
      "classId": 10,
      "studentName": "Marcos Ezequiel Rodriguez",
      "status": "accepted",
      "id": 2
    },
    {
      "userId": 1,
      "classId": 10,
      "name": "Cosme Fulano",
      "status": "accepted",
      "id": 3
    }
  ],
  "classes_reviews": [
    {
      "userId": 1,
      "professorId": 2,
      "classId": 10,
      "studentName": "Marcos Ezequiel Rodriguez",
      "rating": 5,
      "id": 1,
      "comment": {
        "date": "2022-09-17T01:02:50.864Z",
        "status": "sent",
        "message": "test"
      }
    }
  ]
}
